{
  "metadata": {
    "total_records": 15,
    "generated_at": "2025-11-30T17:42:35.102583Z",
    "version": "1.4",
    "keywords": [
      "bola88",
      "slot gacor77. maxwin44"
    ]
  },
  "data": [
    {
      "id": "00000438",
      "title": "SLOT ASIA : Link Situs Resmi Slot Gacor Maxwin Hari Ini Server Asia...",
      "url": "https://q-klinika.ru/office/spb-zhukova/",
      "domain": "q-klinika.ru",
      "screenshot_status": "success",
      "detection_api_response": {
        "success": true,
        "result": {
          "status": "non_gambling",
          "prob_vit": 0.0113,
          "prob_ocr": 0.012,
          "prob_fusion": 0.0116,
          "label_vit": "non_gambling",
          "label_ocr": "non_gambling",
          "label_fusion": "non_gambling",
          "detections": [],
          "ocr_text": null,
          "visualization_path": "/results/inference/0f8d5eef-65f6-4eef-8fef-88c13ebdf6bd.jpg",
          "id": "d5a5ad15-3061-4963-b492-599dbc647a40",
          "timestamp": "2025-12-01T00:42:12.339014"
        }
      },
      "detection_status": "success"
    },
    {
      "id": "00000439",
      "title": "Slot Asia : Daftar Platform Link Slot Online 2025 & Link Slot 777 Gacor...",
      "url": "https://nop2030.ru/",
      "domain": "nop2030.ru",
      "screenshot_status": "success",
      "detection_api_response": {
        "success": true,
        "result": {
          "status": "non_gambling",
          "prob_vit": 0.0048,
          "prob_ocr": 0.0,
          "prob_fusion": 0.0024,
          "label_vit": "non_gambling",
          "label_ocr": "non_gambling",
          "label_fusion": "non_gambling",
          "detections": [],
          "ocr_text": null,
          "visualization_path": "/results/inference/1b2b246e-76db-4371-ac64-9ac35fa5beef.jpg",
          "id": "c85fcf7b-a382-4c26-adee-7468d4c1ce23",
          "timestamp": "2025-12-01T00:42:13.138478"
        }
      },
      "detection_status": "success"
    },
    {
      "id": "00000440",
      "title": "IPKSLOT : Agen Situs Slot Gacor Resmi 2025 & Link Slot Online...",
      "url": "https://catalogfair.ru/galleries/bizon",
      "domain": "catalogfair.ru",
      "screenshot_status": "success",
      "detection_api_response": {
        "success": true,
        "result": {
          "status": "non_gambling",
          "prob_vit": 0.0046,
          "prob_ocr": 0.012,
          "prob_fusion": 0.0083,
          "label_vit": "non_gambling",
          "label_ocr": "non_gambling",
          "label_fusion": "non_gambling",
          "detections": [],
          "ocr_text": null,
          "visualization_path": "/results/inference/7e3d433b-aa1a-4937-9cb8-01324ad94216.jpg",
          "id": "8fc3b89a-559b-4ee1-8056-d6a560c995ee",
          "timestamp": "2025-12-01T00:42:16.288354"
        }
      },
      "detection_status": "success"
    },
    {
      "id": "00000441",
      "title": "slot maxwin gacor",
      "url": "https://slot77-maxwin-gacor.blogspot.com/",
      "domain": "slot77-maxwin-gacor.blogspot.com",
      "screenshot_status": "success",
      "detection_api_response": {
        "success": true,
        "result": {
          "status": "gambling",
          "prob_vit": 0.9691,
          "prob_ocr": 1.0,
          "prob_fusion": 0.9846,
          "label_vit": "gambling",
          "label_ocr": "gambling",
          "label_fusion": "gambling",
          "detections": [
            {
              "class": "cta_button",
              "confidence": 0.12847809493541718,
              "bbox": [
                -667.9396362304688,
                889.1090087890625,
                836.2545166015625,
                951.1376953125
              ]
            }
          ],
          "ocr_text": "Acest site foloseste cookie-uri de la Google pentru livrarea serviciilor si analizarea traficului. Adresa dvs. IP si programul user agent sunt trimise cftre Google impreun cu valorile privind performanta si securitatea pentru AFLATI MAI MULTE AM ONTELES asigurarea calitátii serviciului , generarea statisticilor de utilizare, detectarea çi remedierea abuzurilor. BAKAR77\" ACEN SLOT TERPE BKA77 LOSE ST gqMusZD% MASUK DAFTAR Soor Csno Slor TembakKan Geor8 Jao oT 6,669,523,248.76 BCA maniri BNI 5 Ovo gopay RTP Gacor dana Ca Shul Jenius E Kerbal Alnn Say Premesi Gegar ena DAFTAR BAKAR77 Postingan Terbaru LINK ALTERNATIF AGEN TARUHAN CASINO AGEN TARUHAN CASINO SBOBET SPIINER BAKAR77 BAKAR77 SLOT SBOBET DEPOSIT 50 RIBU BAKAR77 BAKAR77 SLOT Situs Judi PGSOFT LOGO PNG MAIN SLOT DEPOSIT 50 RIBU, PGSOFT LOGO PNG, Online Gampang menang BAKAR77 ONLINE MAIN SLOT ONLINE BAKAR77 Slot online BAKAR77 ZNE Terpercaya Gampang Menang dan AGEN SBOBET ialah hacker6z web judi bola online Mudah Maxwin Slot Online BAKAR77 G\" Sangat Gacor Gampang Maxwin dapat dipercaya di Indonesia yang sediakan pasaran Bakar77 bakar77: Situs Judi Slot Maupun taruhan judi bola terkomp - Togel Online Tergacor bakar77: Situs 24 Judi Slot Maupun Togel Online Tergacor Jam Rabu 16 November 2022 Tambah Komentar BAKAR77 web judi slot; pragmatic play terpercaya dan terbaru BAKAR77 bet77 terpercaya situs infini88 gacor BAKAR77 | Slot Gacor indonesia terbaik 2023 Ngobrol Yukı online BAKAP77 slot freebet terbaik di RIKES",
          "visualization_path": "/results/inference/724f3160-3559-4f89-9806-a9b771e7fe70.jpg",
          "id": "14337b6c-25ce-45f5-aee3-48416ce8aa99",
          "timestamp": "2025-12-01T00:42:15.649086"
        }
      },
      "detection_status": "success"
    },
    {
      "id": "00000442",
      "title": "Slotbom77 ~ Slot Demo Gacor Paling Ekstrim Tergila Modal Jari Auto...",
      "url": "https://slotbom77sensa.com/",
      "domain": "slotbom77sensa.com",
      "screenshot_status": "success",
      "detection_api_response": {
        "success": true,
        "result": {
          "status": "gambling",
          "prob_vit": 0.9846,
          "prob_ocr": 1.0,
          "prob_fusion": 0.9923,
          "label_vit": "gambling",
          "label_ocr": "gambling",
          "label_fusion": "gambling",
          "detections": [
            {
              "class": "logo",
              "confidence": 0.2019326537847519,
              "bbox": [
                365.4606018066406,
                66.3598861694336,
                568.3145751953125,
                118.95361328125
              ]
            },
            {
              "class": "cta_button",
              "confidence": 0.18592387437820435,
              "bbox": [
                1329.5140380859375,
                4.782188415527344,
                1436.8369140625,
                41.597740173339844
              ]
            },
            {
              "class": "menu_nav",
              "confidence": 0.18146733939647675,
              "bbox": [
                677.126220703125,
                64.80009460449219,
                1519.267822265625,
                117.5577163696289
              ]
            },
            {
              "class": "cta_button",
              "confidence": 0.15690740942955017,
              "bbox": [
                1443.4853515625,
                5.290720462799072,
                1538.2337646484375,
                41.773773193359375
              ]
            },
            {
              "class": "banner_promo",
              "confidence": 0.15158352255821228,
              "bbox": [
                0.8600807189941406,
                136.83241271972656,
                1903.71728515625,
                731.8467407226562
              ]
            }
          ],
          "ocr_text": "Whatsapp Telegram 0 Livechar DAFTAR LOGIN [026 SLOTBSMI BERANDA SLOT ONLINE LIVE CASINO SPORTSBOOK ARCADE TOGEL ONLINE POKER SL TB JMI7 Slt Gacon 28239 @rsbiim MODAL JARI AUTO MAXWIN CUAN PROGRESSSIVE JACKPOT RP {86.039.273.241842 LIVECHAT 4",
          "visualization_path": "/results/inference/3e49e832-3122-467c-b643-7838201d9368.jpg",
          "id": "2dcbd64d-d365-47a5-9e68-8c7facd3688d",
          "timestamp": "2025-12-01T00:42:20.834601"
        }
      },
      "detection_status": "success"
    },
    {
      "id": "00000443",
      "title": "Tren Slot Gacor Hari Ini Yang Sedang Populer Di... - Viamalghe",
      "url": "https://viamalghe.com/tren-slot-gacor-hari-ini-yang-sedang-populer-di-kalangan-pemain/",
      "domain": "viamalghe.com",
      "screenshot_status": "success",
      "detection_api_response": {
        "success": true,
        "result": {
          "status": "gambling",
          "prob_vit": 0.0146,
          "prob_ocr": 1.0,
          "prob_fusion": 0.5073,
          "label_vit": "non_gambling",
          "label_ocr": "gambling",
          "label_fusion": "gambling",
          "detections": [],
          "ocr_text": "SEO PROMAX Viamalghe SEO ProMax Tren Slot Gacor Hari Ini Yang Sedang Populer Di Kalangan Blogroll / Sidebar topltoto Pemain kartutoto Posted on November 7, 2025 5.50 pm Comment petir108 Dalam beberapa waktu terakhir, perhatian pemain slot online tertuju pada fenomena slot gacor hari ini yang semakin diminati . Pola slot gampang menang kemenangan yang konsisten dan kesempatan meraih slot maxwin membuat tren ini menjadi topik hangat di berbagai komunitas penggemar kartutoto permainan daring. Pengamat permainan digital menilai bahwa pemahaman tentang ritme mesin dan pengelolaan modal menjadi kunci utama untuk memanfaatkan peluang ini secara maksimal. link slot gacor situs slot gacor Faktor Yang Membuat Slot Gacor Terbaru Menarik Bagi topltoto gacor gacor",
          "visualization_path": "/results/inference/e7a41145-0dfe-4231-8d3c-4fa6b86066af.jpg",
          "id": "687000df-cbcd-473f-8c6c-3648514bdfc4",
          "timestamp": "2025-12-01T00:42:17.718609"
        }
      },
      "detection_status": "success"
    },
    {
      "id": "00000444",
      "title": "Dewi288 Link Login Maxi188 Slot Gacor Server Thailand 2026.",
      "url": "https://bluescopezacs.id/help/home",
      "domain": "bluescopezacs.id",
      "screenshot_status": "success",
      "detection_api_response": {
        "success": true,
        "result": {
          "status": "non_gambling",
          "prob_vit": 0.0079,
          "prob_ocr": 0.1174,
          "prob_fusion": 0.0627,
          "label_vit": "non_gambling",
          "label_ocr": "non_gambling",
          "label_fusion": "non_gambling",
          "detections": [],
          "ocr_text": null,
          "visualization_path": "/results/inference/ad2eaf44-8666-4ff0-a8ec-8780bef5f443.jpg",
          "id": "ef01b9c1-d16e-4ef8-85b8-b7444b08794b",
          "timestamp": "2025-12-01T00:42:18.375885"
        }
      },
      "detection_status": "success"
    },
    {
      "id": "00000445",
      "title": "OHTOGEL Layanan Resep Prediksi Toto Togel 4D & Toto Slot ...",
      "url": "https://imccsub.com/preload",
      "domain": "imccsub.com",
      "screenshot_status": "success",
      "detection_api_response": {
        "success": true,
        "result": {
          "status": "non_gambling",
          "prob_vit": 0.0399,
          "prob_ocr": 0.0387,
          "prob_fusion": 0.0393,
          "label_vit": "non_gambling",
          "label_ocr": "non_gambling",
          "label_fusion": "non_gambling",
          "detections": [],
          "ocr_text": null,
          "visualization_path": "/results/inference/5f57d0d2-51fe-4501-87ca-b57a75751ee5.jpg",
          "id": "1a6520b2-2e49-438b-abb2-6eaf87643180",
          "timestamp": "2025-12-01T00:42:19.796557"
        }
      },
      "detection_status": "success"
    },
    {
      "id": "00000446",
      "title": "Daftar Slot Gacor Terpercaya Dengan Slot 88 Mudah Maxwin Hari",
      "url": "https://blockingup.com/link-resmi-daftar-slot-gacor-terpercaya/",
      "domain": "blockingup.com",
      "screenshot_status": "success",
      "detection_api_response": {
        "success": true,
        "result": {
          "status": "gambling",
          "prob_vit": 0.9957,
          "prob_ocr": 1.0,
          "prob_fusion": 0.9979,
          "label_vit": "gambling",
          "label_ocr": "gambling",
          "label_fusion": "gambling",
          "detections": [
            {
              "class": "banner_promo",
              "confidence": 0.23735977709293365,
              "bbox": [
                452.38323974609375,
                175.18728637695312,
                1453.6385498046875,
                516.9881591796875
              ]
            },
            {
              "class": "menu_nav",
              "confidence": 0.11394166946411133,
              "bbox": [
                525.918212890625,
                90.48945617675781,
                941.1637573242188,
                122.7060775756836
              ]
            }
          ],
          "ocr_text": "Situs Agen Game Terpopuler Cari MEGA PRAGMATIC (PLAY GACOR Wheel drops Hivgguay & Turhahev hariak RPBBMILIAR hadiah uavg Tuvai berlangsuwg hixgga J0 Maret 2026 Home Judi Bola Poker Online Slot Online Togel Online Sebelumnya Selanjutnya Judi Slot Gacor Pragmatic Play Ditulis pada November 2025 Table of Contents 1. Link Resmi Daftar Slot Gacor Terpercaya Dengan Slot88 Mudah Maxwin Hari Ini Terbaik 2.Link Resmi Daftar Slot Gacor Terpercaya Dengan Slot88 Mudah Maxwin Hari Ini Terbaik 2.1. Link Resmi Terpercaya Dengan Slot88 Mudah Maxwin Hari Ini Terbaik DaILY WIns",
          "visualization_path": "/results/inference/10803133-81f2-45c5-b8dd-cffd884ba6bf.jpg",
          "id": "d1652ae1-1012-446f-9cab-aedca28e5a04",
          "timestamp": "2025-12-01T00:42:22.157216"
        }
      },
      "detection_status": "success"
    },
    {
      "id": "00000447",
      "title": "Best Online Slot Sites: Best Slots to Play Online for Real Money ...",
      "url": "https://www.rotowire.com/betting/casinos/slot-sites",
      "domain": "www.rotowire.com",
      "screenshot_status": "success",
      "detection_api_response": {
        "success": true,
        "result": {
          "status": "gambling",
          "prob_vit": 0.6191,
          "prob_ocr": 1.0,
          "prob_fusion": 0.8095,
          "label_vit": "gambling",
          "label_ocr": "gambling",
          "label_fusion": "gambling",
          "detections": [
            {
              "class": "cta_button",
              "confidence": 0.1805446594953537,
              "bbox": [
                1285.8824462890625,
                13.600332260131836,
                1362.05859375,
                46.04191589355469
              ]
            },
            {
              "class": "menu_nav",
              "confidence": 0.1361810863018036,
              "bbox": [
                253.49610900878906,
                15.824854850769043,
                876.7232666015625,
                43.55751037597656
              ]
            }
          ],
          "ocr_text": "rotowire Fantasy DFS 7 Betting Picks & Props Up Login Search For Player RotoWire > Betting Slot Sites Best Online Slot Sites: Best U.S Slots to Online for Real Money November 2025 Author: Tyler Olson Last Updated: Oct 28,2025 Fact Checked By: PJ Wright The best slot sites are legal U.S.online casinos that offer hundreds of real-money slot games, including classics; progressive jackpots and exclusive titles Top-rated platforms like BetMGM; Caesars and bet365, among others, provide fast payouts; mobile apps and secure gameplay for slot players in legal U.S. states. Top Rated Brand 1009 Deposit Match GET OFFER HERE BETMGM Up to $1,000 Plus $25 Sign Up Bonus On The House PLAY NOW Pay Gambling Problem? Call 1-800-GAMBLER. Must be 21+. MI, NJ, PA and WV only New Customers Only: Please Gamble Responsibly . Visit [http:l/BetMGM .com http-l[BetMGM com/] for Terms and Conditions. All promotions are subject to qualification and eligibility requirements Rewards issued as non-withdrawable site credit/Bonus Bets unless otherwise provided in the applicable terms. Rewards subject to expiry Top Rated Brand bet365 100% Deposit Match GET OFFER HERE Casino Bonus up to $1,000 + Sign Up Bonus up to 500 Spins PLAY NOW We value your privacy We and our 1544partners use cookies and other tracking technologies to improve your experience on our website We may store andlor access information on a device and process personal data; such as your IP address and browsing data, for personalised advertising and content; advertising and content measurement; audience research and services development . Additionally; we may utilize precise geolocation data and identification through device scanning: Customise Reject AIl Accept AIl Please note that your consent will be valid across all our subdomains. Once you give consent, a floating button will appear at the bottom of your screen; allowing you to change or withdraw your consent at any time We respect your choices and are committed to providing you with a transparent and secure browsing experience. Cookie Policy Sin ' Play",
          "visualization_path": "/results/inference/fd8ea09d-ea7a-47ad-91c8-6990b0f509bb.jpg",
          "id": "baac889a-4ba5-40f9-baea-cc2dcbe51591",
          "timestamp": "2025-12-01T00:42:24.828820"
        }
      },
      "detection_status": "success"
    },
    {
      "id": "00000448",
      "title": "Bola88 Review - Top 100 Bookmakers",
      "url": "https://www.top100bookmakers.com/bookies_bola88.php",
      "domain": "www.top100bookmakers.com",
      "screenshot_status": "success",
      "detection_api_response": {
        "success": true,
        "result": {
          "status": "non_gambling",
          "prob_vit": 0.0881,
          "prob_ocr": 0.4677,
          "prob_fusion": 0.2779,
          "label_vit": "non_gambling",
          "label_ocr": "non_gambling",
          "label_fusion": "non_gambling",
          "detections": [],
          "ocr_text": null,
          "visualization_path": "/results/inference/ad5ba26d-34ae-42f8-96ae-56489cf1b4a5.jpg",
          "id": "ac855753-8eb2-4bb0-9c43-f143db4f7e01",
          "timestamp": "2025-12-01T00:42:26.874363"
        }
      },
      "detection_status": "success"
    },
    {
      "id": "00000449",
      "title": "BOLAGILA - Situs Judi Slot Gacor Maxwin Terbaru 24 Jam",
      "url": "https://www.bolagila.com/",
      "domain": "www.bolagila.com",
      "screenshot_status": "success",
      "detection_api_response": {
        "success": true,
        "result": {
          "status": "non_gambling",
          "prob_vit": 0.2514,
          "prob_ocr": 0.3417,
          "prob_fusion": 0.2965,
          "label_vit": "non_gambling",
          "label_ocr": "non_gambling",
          "label_fusion": "non_gambling",
          "detections": [],
          "ocr_text": null,
          "visualization_path": "/results/inference/2ef675e6-6058-44db-8719-816e7734cf46.jpg",
          "id": "725656f8-1b7a-4bf9-b46a-064dc0fac4ee",
          "timestamp": "2025-12-01T00:42:35.014303"
        }
      },
      "detection_status": "success"
    },
    {
      "id": "00000450",
      "title": "Bola88 Review: Bonus Codes, Registration and Mobile Apps",
      "url": "https://www.telecomasia.net/sports-betting/reviews/bola88/",
      "domain": "www.telecomasia.net",
      "screenshot_status": "success",
      "detection_api_response": {
        "success": true,
        "result": {
          "status": "gambling",
          "prob_vit": 0.6729,
          "prob_ocr": 0.61,
          "prob_fusion": 0.6414,
          "label_vit": "gambling",
          "label_ocr": "gambling",
          "label_fusion": "gambling",
          "detections": [
            {
              "class": "cta_button",
              "confidence": 0.10959044843912125,
              "bbox": [
                1474.994384765625,
                6.58901309967041,
                1586.697265625,
                39.623207092285156
              ]
            }
          ],
          "ocr_text": "[TILECOM ASIA SPORT #x EN Sports Betting Betting Tips Bonuses & Offers News   Betting Statistics Events Search Bonus $100 Sign in Feed Customize Home Sports Betting Reviews Bola88 News MMA Hot News Bulh Aspinall Publishes Medical Report on Eye Injury Sustained Write a Review Bola88 Review: Bonus Codes, from Gane's Eye Poke New To top Registration and Mobile Apps 34 minutes ago 1 Review Prediction 2 Pros & Cons Bet Now! 0: 2,05 3 Legality & Safety of 30 Nov 2025   23.00 Bola88 in Indonesia Utah Jazz vs Houston Rockets 4 Bonuses Bonus: 50 USD Claim Bonus Prediction: Houston Poised to 5. Mobile Sports Betting Dominate Struggling Utah 6. Bola88 Sports Login Defense and Sign Up Margin: Cash Out: Live Streaming: today 30 Nov 2025 17.35 7 Markets and Sports 5 - 99 No Yes lines Prediction 8. Info 0: 2,05 9 Contacts of a Bookie Download 30 Nov 2025   22*45 10. FAQ Roma vs Napoli Prediction: Download from Download from App Store Google Play Roma and Napoli Set for a Low- Scoring Clash today 30 Nov 2025 17.00 Prediction 1 Review 0: 1,8 Bola88 is a reliable bookmaker in Indonesia that offers many wagering alternatives to new and 30 Nov 2025  21.30 Freiburg vs Mainz Prediction: Is This website uses cookies agree there a light at the end of the This provides customers with a personalized experience and increases the efficiency of visiting the site, allowing us to provide tunnel for Mainz? the most efficient service. By using the website and accepting the terms of the policy; you consent to the use of cookies in accordance with the terms of this policy. today; 30 Nov 2025 16.36 Ioon Blog App",
          "visualization_path": "/results/inference/843a9658-1765-40eb-9fef-c1414e86f197.jpg",
          "id": "5e3d897a-bb87-45b8-aa42-632a565847ed",
          "timestamp": "2025-12-01T00:42:29.431762"
        }
      },
      "detection_status": "success"
    },
    {
      "id": "00000451",
      "title": "Bola88 Review by Online Casino City",
      "url": "https://online.casinocity.com/sportsbooks/bola88/",
      "domain": "online.casinocity.com",
      "screenshot_status": "success",
      "detection_api_response": {
        "success": true,
        "result": {
          "status": "gambling",
          "prob_vit": 0.0106,
          "prob_ocr": 1.0,
          "prob_fusion": 0.5053,
          "label_vit": "non_gambling",
          "label_ocr": "gambling",
          "label_fusion": "gambling",
          "detections": [
            {
              "class": "menu_nav",
              "confidence": 0.10531383007764816,
              "bbox": [
                5.719449520111084,
                18.115814208984375,
                199.92115783691406,
                80.81316375732422
              ]
            },
            {
              "class": "logo",
              "confidence": 0.10494786500930786,
              "bbox": [
                5.719449520111084,
                18.115814208984375,
                199.92115783691406,
                80.81316375732422
              ]
            },
            {
              "class": "menu_nav",
              "confidence": 0.10137243568897247,
              "bbox": [
                214.21803283691406,
                16.380834579467773,
                723.316162109375,
                84.78216552734375
              ]
            }
          ],
          "ocr_text": "online Search Cesino avanceg searcn Your Guide to Gaming Excltement MY PREFERENGES Language: Bola88 Rankings At A Glance English Poe Bolagg is an online sportsbook also offering baccarat esports, live dealer games; livelin-play betting , other 325th 0f569 in Non-English sportsbook Location: games, poker; roulette using IDNPLAY and Qriental Game software.  The site's primary language 3rd of 54 in IDNPLAY Sites Romania is Indonesian. It supports both downloadable software and the ability to place a wager without à download . 3rd of 38 in Oriental Game Sites Bola88 runs on the IDNPoker network Currency: 1787t of 4613 in Online Gaming Sites Any Currency Visit Bolagg edit my_preferences Home Online Slots Bola88 Live Dealer Games Live Dealer Games Roulette Baccarat Baccarat Squeeze Dragon Iiger Online Casinos Bola88 URLs Online Poker Online Bingo gx02B92P8E9TaRasasadodesesiandonmaasie 830 gy_bola8g_comMain aspx?langzEN AU Bahasa indonesia  (Indonesian) Games gybola8g comMainaspxzlang-EME Tiéng Vi$t   (Vietnamese) Lotteries gybola8g comMainaspxzlangzENI DI  (Korean) gy bola8g comMainaspxzlangzENus English Sponts Racebooks gy bola8g comMainaspxzlangZTHTF JwzID (Thai) gy_bola8g comiainaspxzlangEzZHCN (Simplified Chinese) Fantasy Sports mbola8g com Bahasa indonesia (Indonesian) ubolagginfo Bahasa indonesia   (Indonesian) fair Forex Betting Exchanges Support & Contact Information Supported Languages Spread Betting Support Option E-mail Entry Form; and Live Chat:. English, Indonesian; Korean; Simplified Binary Options Chinese;Thai, and Vietnamese. Exclusive Bonuses ErrorslOmissions? If there are any inaccuracies in our data , please Let Us Knowl Currencies Accepted Weekly Newsletter Indonesian Rupiahs Online Gaming News Payment Methods Payment Methods For Deposits Only Automated Ieler Machine _(AIM. Cash Gaming Software nteret Banking, and Mobile Billing Pay_bx Phone Gaming Site Owners For Deposits and Withdrawals DirectLocaVFast Bank Iansfers Gaming Jurisdictions Cty and casino the",
          "visualization_path": "/results/inference/dc2cf8f0-66e1-457c-8f9b-21a0fd45d580.jpg",
          "id": "4d5e3a1a-ca81-4491-8592-e32563fd81b8",
          "timestamp": "2025-12-01T00:42:32.195167"
        }
      },
      "detection_status": "success"
    },
    {
      "id": "00000452",
      "title": "Bola88 : Bandar Judi Bola Terpercaya Gacor | Login Bola 88",
      "url": "https://206.189.84.164/",
      "domain": "206.189.84.164",
      "screenshot_status": "success",
      "detection_api_response": {
        "success": true,
        "result": {
          "status": "non_gambling",
          "prob_vit": 0.6657,
          "prob_ocr": 0.04,
          "prob_fusion": 0.3529,
          "label_vit": "gambling",
          "label_ocr": "non_gambling",
          "label_fusion": "non_gambling",
          "detections": [],
          "ocr_text": null,
          "visualization_path": "/results/inference/b6fb71ce-0bbd-4c4e-8dfe-b1b95d47cc81.jpg",
          "id": "4aad5e0e-94dc-4e93-b503-990cbc62b27c",
          "timestamp": "2025-12-01T00:42:33.179044"
        }
      },
      "detection_status": "success"
    }
  ]
}